governor/__init__.py
governor/decorator.py
governor/approval/__init__.py
governor/approval/handlers.py
governor/approval/manager.py
governor/background/__init__.py
governor/background/queue.py
governor/background/resume.py
governor/compliance/__init__.py
governor/compliance/gdpr.py
governor/compliance/reporter.py
governor/compliance/soc2.py
governor/config/__init__.py
governor/config/loader.py
governor/core/__init__.py
governor/core/context.py
governor/core/executor.py
governor/core/state.py
governor/dashboard/__init__.py
governor/dashboard/server.py
governor/events/__init__.py
governor/events/base.py
governor/events/emitter.py
governor/integrations/__init__.py
governor/integrations/fastapi.py
governor/policies/__init__.py
governor/policies/approval.py
governor/policies/audit.py
governor/policies/authorization.py
governor/policies/base.py
governor/policies/rate_limit.py
governor/policies/sequential_approval.py
governor/policies/validation.py
governor/replay/__init__.py
governor/replay/engine.py
governor/storage/__init__.py
governor/storage/base.py
governor/storage/memory.py
governor/storage/mongodb.py
governor/utils/__init__.py
governor/utils/serialization.py
governor-0.2.0.dist-info/METADATA
governor-0.2.0.dist-info/WHEEL
governor-0.2.0.dist-info/licenses/LICENSE
governor-0.2.0.dist-info/RECORD
