Metadata-Version: 2.4
Name: governor
Version: 0.2.0
Summary: A clean, minimal governance library for agentic systems with state management, policies, and human-in-the-loop support
Project-URL: Homepage, https://github.com/shreyas-lyzr/governor
Project-URL: Documentation, https://github.com/shreyas-lyzr/governor#readme
Project-URL: Repository, https://github.com/shreyas-lyzr/governor
Project-URL: Issues, https://github.com/shreyas-lyzr/governor/issues
Project-URL: Changelog, https://github.com/shreyas-lyzr/governor/releases
Author: governor contributors
License: MIT
License-File: LICENSE
Keywords: agentic,agents,governance,human-in-the-loop,policy,state-management
Classifier: Development Status :: 4 - Beta
Classifier: Intended Audience :: Developers
Classifier: License :: OSI Approved :: MIT License
Classifier: Programming Language :: Python :: 3
Classifier: Programming Language :: Python :: 3.9
Classifier: Programming Language :: Python :: 3.10
Classifier: Programming Language :: Python :: 3.11
Classifier: Programming Language :: Python :: 3.12
Classifier: Topic :: Software Development :: Libraries :: Python Modules
Requires-Python: >=3.9
Requires-Dist: pydantic>=2.0.0
Requires-Dist: typing-extensions>=4.5.0
Provides-Extra: all
Requires-Dist: build>=1.0.0; extra == 'all'
Requires-Dist: fastapi>=0.104.0; extra == 'all'
Requires-Dist: motor>=3.3.0; extra == 'all'
Requires-Dist: mypy>=1.5.0; extra == 'all'
Requires-Dist: pytest-asyncio>=0.21.0; extra == 'all'
Requires-Dist: pytest-cov>=4.1.0; extra == 'all'
Requires-Dist: pytest>=7.4.0; extra == 'all'
Requires-Dist: pyyaml>=6.0.0; extra == 'all'
Requires-Dist: ruff>=0.1.0; extra == 'all'
Requires-Dist: twine>=4.0.0; extra == 'all'
Requires-Dist: uvicorn[standard]>=0.24.0; extra == 'all'
Requires-Dist: websockets>=12.0; extra == 'all'
Provides-Extra: dashboard
Requires-Dist: fastapi>=0.104.0; extra == 'dashboard'
Requires-Dist: uvicorn[standard]>=0.24.0; extra == 'dashboard'
Requires-Dist: websockets>=12.0; extra == 'dashboard'
Provides-Extra: dev
Requires-Dist: build>=1.0.0; extra == 'dev'
Requires-Dist: mypy>=1.5.0; extra == 'dev'
Requires-Dist: pytest-asyncio>=0.21.0; extra == 'dev'
Requires-Dist: pytest-cov>=4.1.0; extra == 'dev'
Requires-Dist: pytest>=7.4.0; extra == 'dev'
Requires-Dist: ruff>=0.1.0; extra == 'dev'
Requires-Dist: twine>=4.0.0; extra == 'dev'
Provides-Extra: fastapi
Requires-Dist: fastapi>=0.104.0; extra == 'fastapi'
Provides-Extra: mongodb
Requires-Dist: motor>=3.3.0; extra == 'mongodb'
Provides-Extra: yaml
Requires-Dist: pyyaml>=6.0.0; extra == 'yaml'
